duck/__init__.py
duck/batch.py
duck/flow.py
duck/loss.py
duck/py.typed
duck/ros.py
duck/time.py
duck/types.py
duck/device/__init__.py
duck/device/rydberg.py
duck/opmap/__init__.py
duck/opmap/abc.py
duck/opmap/hem/__init__.py
duck/opmap/hem/mlp.py
duck/opmap/omm/__init__.py
duck/opmap/omm/mlp.py
duck/opmap/omm/mps.py
duck/ops/__init__.py
duck/ops/abc.py
duck/ops/const.py
duck/ops/place.py
duck/ops/sum.py
duck/ops/time_dependent.py
duck/ops/zero.py
duck/rescalable/__init__.py
duck/rescalable/a.py
duck/rescalable/abc.py
duck/rescalable/site.py
duck/rescalable/str.py
duck/rescalable/chain/__init__.py
duck/rescalable/chain/ab.py
duck/rescalable/chain/ham.py
duck/solve/__init__.py
duck/solve/realtime.py
duck/task/__init__.py
duck/task/abc.py
duck/task/config.py
duck/task/env.py
duck/task/gradually.py
duck/task/together.py
duck/task/logging/__init__.py
duck/task/logging/json_like.py
duck/task/logging/toml.py
duck/task/logging/wandb.py
rogerluo_duck-0.3.2.dist-info/METADATA
rogerluo_duck-0.3.2.dist-info/WHEEL
rogerluo_duck-0.3.2.dist-info/licenses/LICENSE
rogerluo_duck-0.3.2.dist-info/RECORD
