Metadata-Version: 2.3
Name: rogerluo-duck
Version: 0.3.2
Summary: A software framework for the duck (operator learning) renormalization group.
Author-email: Roger-luo <rogerluo.rl18@gmail.com>
Requires-Python: >=3.12
Requires-Dist: diffrax>=0.6.0
Requires-Dist: equinox>=0.11.8
Requires-Dist: jax>=0.4.35
Requires-Dist: jaxtyping>=0.2.34
Requires-Dist: optax>=0.2.3
Requires-Dist: pydantic>=2.9.2
Requires-Dist: rich>=13.9.3
Requires-Dist: tomlkit>=0.13.2
Requires-Dist: tqdm>=4.67.1
Requires-Dist: typing-extensions>=4.12.2
Provides-Extra: gpu
Requires-Dist: jax[cuda12]>=0.4.35; extra == 'gpu'
Provides-Extra: plot
Requires-Dist: matplotlib>=3.9.2; extra == 'plot'
Provides-Extra: wandb
Requires-Dist: wandb>=0.18.5; extra == 'wandb'
